clara/__init__.py
clara/animation.py
clara/brain.py
clara/knowledge_graph.py
clara/message_statistics.py
clara/ml_engine.py
clara/modelTrainer.py
clara/server.py
clara/test.py
clara/tokenizer.py
clara/web.py
clara/utils/:w
clara/utils/__init__.py
clara/utils/convo_reader.py
clara/utils/iograb.py
clara/utils/sentiment.py
clara/utils/server.py
clara/utils/story_reader.py
clara/utils/t_story.py
clara-1.4.0.data/scripts/clara
clara-1.4.0.dist-info/LICENSE
clara-1.4.0.dist-info/METADATA
clara-1.4.0.dist-info/WHEEL
clara-1.4.0.dist-info/top_level.txt
clara-1.4.0.dist-info/RECORD
