Metadata-Version: 2.1
Name: clara
Version: 1.4.0
Summary: Conversational chit-chat utility agent
Home-page: https://github.com/huberf/clara-pip
Author: Noah Huber-Feely
Author-email: nhuberfeely@gmail.com
License: UNKNOWN
Download-URL: https://github.com/huberf/clara-pip/archive/1.4.0.tar.gz
Keywords: clara,chat
Platform: UNKNOWN
Requires-Dist: flask
Requires-Dist: python-Levenshtein
Requires-Dist: vaderSentiment
